ossindex_api_client/__init__.py
ossindex_api_client/api/__init__.py
ossindex_api_client/api/component_vulnerability_reports_api.py
ossindex_api_client/api/version_api.py
ossindex_api_client/api_client.py
ossindex_api_client/api_response.py
ossindex_api_client/configuration.py
ossindex_api_client/exceptions.py
ossindex_api_client/models/__init__.py
ossindex_api_client/models/component_report.py
ossindex_api_client/models/component_report_request.py
ossindex_api_client/models/component_report_vulnerability.py
ossindex_api_client/models/version.py
ossindex_api_client/py.typed
ossindex_api_client/rest.py
ossindex_api_client-2025.320.0.dist-info/METADATA
ossindex_api_client-2025.320.0.dist-info/WHEEL
ossindex_api_client-2025.320.0.dist-info/RECORD
