Metadata-Version: 2.1
Name: ossindex_api_client
Version: 2025.320.0
Summary: Sonatype OSS Index
Home-page: https://github.com/sonatype-nexus-community/ossindex-api-client
License: Apache 2.0
Keywords: OpenAPI,OpenAPI-Generator,Sonatype OSS Index
Author: Sonatype Community Maintainers
Author-email: community@sonatype.com
Requires-Python: >=3.8,<4.0
Classifier: License :: Other/Proprietary License
Classifier: Programming Language :: Python :: 3
Classifier: Programming Language :: Python :: 3.8
Classifier: Programming Language :: Python :: 3.9
Classifier: Programming Language :: Python :: 3.10
Classifier: Programming Language :: Python :: 3.11
Classifier: Programming Language :: Python :: 3.12
Requires-Dist: pydantic (>=2)
Requires-Dist: python-dateutil (>=2.8.2)
Requires-Dist: typing-extensions (>=4.7.1)
Requires-Dist: urllib3 (>=1.25.3,<3.0.0)
Project-URL: Repository, https://github.com/sonatype-nexus-community/ossindex-api-client
